pyAEATsii/__init__.py
pyAEATsii/callback_utils.py
pyAEATsii/mapping.py
pyAEATsii/plugins.py
pyAEATsii/service.py
pyAEATsii-1.1.2.dist-info/LICENSE
pyAEATsii-1.1.2.dist-info/METADATA
pyAEATsii-1.1.2.dist-info/WHEEL
pyAEATsii-1.1.2.dist-info/top_level.txt
pyAEATsii-1.1.2.dist-info/RECORD
