Metadata-Version: 2.1
Name: pyAEATsii
Version: 1.1.2
Summary: A python wrapper for the AEAT SII webservices
Home-page: http://www.calidae.com/
Author: Calidae S.L.
Author-email: dev@calidae.com
License: UNKNOWN
Download-URL: https://github.com/calidae/python-aeat_sii
Platform: UNKNOWN
Classifier: Programming Language :: Python :: 2
Classifier: Programming Language :: Python :: 2.7
Classifier: Programming Language :: Python :: 3
Classifier: Programming Language :: Python :: 3.3
Classifier: Programming Language :: Python :: 3.4
Classifier: Programming Language :: Python :: 3.5
Classifier: Programming Language :: Python :: 3.6
Classifier: Programming Language :: Python :: Implementation :: CPython
Classifier: Programming Language :: Python :: Implementation :: PyPy
Requires-Dist: zeep (>=1.6)
Provides-Extra: test
Requires-Dist: pytest (>3) ; extra == 'test'
Requires-Dist: mock ; extra == 'test'
